faas/__init__.py
faas/app.py
faas/util.py
workshop_faas-0.0.1.dist-info/METADATA
workshop_faas-0.0.1.dist-info/WHEEL
workshop_faas-0.0.1.dist-info/entry_points.txt
workshop_faas-0.0.1.dist-info/top_level.txt
workshop_faas-0.0.1.dist-info/RECORD
