Metadata-Version: 2.1
Name: workshop-faas
Version: 0.0.1
Summary: A faas platform for homelab or workshop setups
Home-page: https://github.com/WorkshopHQ/faas
Author: Tan Li
Author-email: tanl@workshop.cool
Project-URL: Bug Tracker, https://github.com/WorkshopHQ/faas/issues
Classifier: Programming Language :: Python :: 3
Classifier: License :: OSI Approved :: MIT License
Classifier: Operating System :: OS Independent
Requires-Python: >=3.8
Requires-Dist: uvicorn[standard]
Requires-Dist: fastapi
Requires-Dist: typer
Requires-Dist: rich
Requires-Dist: requests
Requires-Dist: python-multipart
Provides-Extra: dev
Requires-Dist: pytest ; extra == 'dev'
Requires-Dist: black ; extra == 'dev'
Requires-Dist: isort ; extra == 'dev'
Requires-Dist: flake8 ; extra == 'dev'
Requires-Dist: mkdocs-material ; extra == 'dev'
